<?xml version="1.0" standalone="yes"?>
<NewDataSet>
  <Sys_MapData>
    <No>ND9004</No>
    <Name>加密器领用申请</Name>
    <EnPK>OID</EnPK>
    <SearchKeys />
    <PTable>ND9004</PTable>
    <Dtls />
    <CellsFrom />
    <CellsX>4</CellsX>
    <CellsY>5</CellsY>
    <FrmW>900</FrmW>
    <FrmH>1200</FrmH>
    <DBURL>0</DBURL>
    <Designer />
    <DesignerUnit />
    <DesignerContext />
    <FK_Flow />
    <FormType>0</FormType>
    <URL />
  </Sys_MapData>
  <Sys_FrmLine>
    <MyPK>Line111103080321</MyPK>
    <FK_MapData>ND9004</FK_MapData>
    <X1>879</X1>
    <Y1>78</Y1>
    <X2>879</X2>
    <Y2>217</Y2>
    <BorderWidth>2</BorderWidth>
    <BorderColor>Black</BorderColor>
    <BorderStyle />
    <X>0</X>
    <Y>0</Y>
  </Sys_FrmLine>
  <Sys_FrmLine>
    <MyPK>Line111103140345</MyPK>
    <FK_MapData>ND9004</FK_MapData>
    <X1>86</X1>
    <Y1>217</Y1>
    <X2>879</X2>
    <Y2>217</Y2>
    <BorderWidth>2</BorderWidth>
    <BorderColor>Black</BorderColor>
    <BorderStyle />
    <X>0</X>
    <Y>0</Y>
  </Sys_FrmLine>
  <Sys_FrmLine>
    <MyPK>Line111103140349</MyPK>
    <FK_MapData>ND9004</FK_MapData>
    <X1>455</X1>
    <Y1>179</Y1>
    <X2>455</X2>
    <Y2>217</Y2>
    <BorderWidth>2</BorderWidth>
    <BorderColor>Black</BorderColor>
    <BorderStyle />
    <X>0</X>
    <Y>0</Y>
  </Sys_FrmLine>
  <Sys_FrmLine>
    <MyPK>Line111103140351</MyPK>
    <FK_MapData>ND9004</FK_MapData>
    <X1>278</X1>
    <Y1>178</Y1>
    <X2>278</X2>
    <Y2>217</Y2>
    <BorderWidth>2</BorderWidth>
    <BorderColor>Black</BorderColor>
    <BorderStyle />
    <X>0</X>
    <Y>0</Y>
  </Sys_FrmLine>
  <Sys_FrmLine>
    <MyPK>Line111103140358</MyPK>
    <FK_MapData>ND9004</FK_MapData>
    <X1>641</X1>
    <Y1>177</Y1>
    <X2>641</X2>
    <Y2>217</Y2>
    <BorderWidth>2</BorderWidth>
    <BorderColor>Black</BorderColor>
    <BorderStyle />
    <X>0</X>
    <Y>0</Y>
  </Sys_FrmLine>
  <Sys_FrmLine>
    <MyPK>Line1111140253520</MyPK>
    <FK_MapData>ND9004</FK_MapData>
    <X1>281.82</X1>
    <Y1>81.82</Y1>
    <X2>281.82</X2>
    <Y2>121.82</Y2>
    <BorderWidth>2</BorderWidth>
    <BorderColor>Black</BorderColor>
    <BorderStyle />
    <X>5</X>
    <Y>5</Y>
  </Sys_FrmLine>
  <Sys_FrmLine>
    <MyPK>Line1111140253521</MyPK>
    <FK_MapData>ND9004</FK_MapData>
    <X1>360</X1>
    <Y1>80.91</Y1>
    <X2>360</X2>
    <Y2>120.91</Y2>
    <BorderWidth>2</BorderWidth>
    <BorderColor>Black</BorderColor>
    <BorderStyle />
    <X>5</X>
    <Y>5</Y>
  </Sys_FrmLine>
  <Sys_FrmLine>
    <MyPK>Line1111140253522</MyPK>
    <FK_MapData>ND9004</FK_MapData>
    <X1>158.82</X1>
    <Y1>41.82</Y1>
    <X2>158.82</X2>
    <Y2>122</Y2>
    <BorderWidth>2</BorderWidth>
    <BorderColor>Black</BorderColor>
    <BorderStyle />
    <X>5</X>
    <Y>5</Y>
  </Sys_FrmLine>
  <Sys_FrmLine>
    <MyPK>Line1111140253523</MyPK>
    <FK_MapData>ND9004</FK_MapData>
    <X1>81.55</X1>
    <Y1>80</Y1>
    <X2>874</X2>
    <Y2>80</Y2>
    <BorderWidth>2</BorderWidth>
    <BorderColor>Black</BorderColor>
    <BorderStyle />
    <X>5</X>
    <Y>5</Y>
  </Sys_FrmLine>
  <Sys_FrmLine>
    <MyPK>Line1111140253524</MyPK>
    <FK_MapData>ND9004</FK_MapData>
    <X1>81.82</X1>
    <Y1>40</Y1>
    <X2>81.82</X2>
    <Y2>175</Y2>
    <BorderWidth>2</BorderWidth>
    <BorderColor>Black</BorderColor>
    <BorderStyle />
    <X>5</X>
    <Y>5</Y>
  </Sys_FrmLine>
  <Sys_FrmLine>
    <MyPK>Line1111140253525</MyPK>
    <FK_MapData>ND9004</FK_MapData>
    <X1>81.82</X1>
    <Y1>173.82</Y1>
    <X2>874</X2>
    <Y2>173.82</Y2>
    <BorderWidth>2</BorderWidth>
    <BorderColor>Black</BorderColor>
    <BorderStyle />
    <X>5</X>
    <Y>5</Y>
  </Sys_FrmLine>
  <Sys_FrmLine>
    <MyPK>Line1111140253526</MyPK>
    <FK_MapData>ND9004</FK_MapData>
    <X1>83.36</X1>
    <Y1>40.91</Y1>
    <X2>874</X2>
    <Y2>40.91</Y2>
    <BorderWidth>2</BorderWidth>
    <BorderColor>Black</BorderColor>
    <BorderStyle />
    <X>5</X>
    <Y>5</Y>
  </Sys_FrmLine>
  <Sys_FrmLine>
    <MyPK>Line1111140253527</MyPK>
    <FK_MapData>ND9004</FK_MapData>
    <X1>83.36</X1>
    <Y1>120.91</Y1>
    <X2>873</X2>
    <Y2>120.91</Y2>
    <BorderWidth>2</BorderWidth>
    <BorderColor>Black</BorderColor>
    <BorderStyle />
    <X>5</X>
    <Y>5</Y>
  </Sys_FrmLine>
  <Sys_FrmLine>
    <MyPK>Line1111140253528</MyPK>
    <FK_MapData>ND9004</FK_MapData>
    <X1>873.09</X1>
    <Y1>40</Y1>
    <X2>873.09</X2>
    <Y2>174</Y2>
    <BorderWidth>2</BorderWidth>
    <BorderColor>Black</BorderColor>
    <BorderStyle />
    <X>5</X>
    <Y>5</Y>
  </Sys_FrmLine>
  <Sys_FrmLine>
    <MyPK>Line1111140255040</MyPK>
    <FK_MapData>ND9004</FK_MapData>
    <X1>281.82</X1>
    <Y1>81.82</Y1>
    <X2>281.82</X2>
    <Y2>121.82</Y2>
    <BorderWidth>2</BorderWidth>
    <BorderColor>Black</BorderColor>
    <BorderStyle />
    <X>5</X>
    <Y>5</Y>
  </Sys_FrmLine>
  <Sys_FrmLine>
    <MyPK>Line1111140255041</MyPK>
    <FK_MapData>ND9004</FK_MapData>
    <X1>360</X1>
    <Y1>80.91</Y1>
    <X2>360</X2>
    <Y2>120.91</Y2>
    <BorderWidth>2</BorderWidth>
    <BorderColor>Black</BorderColor>
    <BorderStyle />
    <X>5</X>
    <Y>5</Y>
  </Sys_FrmLine>
  <Sys_FrmLine>
    <MyPK>Line1111140255042</MyPK>
    <FK_MapData>ND9004</FK_MapData>
    <X1>158.82</X1>
    <Y1>41.82</Y1>
    <X2>158.82</X2>
    <Y2>122</Y2>
    <BorderWidth>2</BorderWidth>
    <BorderColor>Black</BorderColor>
    <BorderStyle />
    <X>5</X>
    <Y>5</Y>
  </Sys_FrmLine>
  <Sys_FrmLine>
    <MyPK>Line1111140255043</MyPK>
    <FK_MapData>ND9004</FK_MapData>
    <X1>81.55</X1>
    <Y1>80</Y1>
    <X2>874</X2>
    <Y2>80</Y2>
    <BorderWidth>2</BorderWidth>
    <BorderColor>Black</BorderColor>
    <BorderStyle />
    <X>5</X>
    <Y>5</Y>
  </Sys_FrmLine>
  <Sys_FrmLine>
    <MyPK>Line1111140255044</MyPK>
    <FK_MapData>ND9004</FK_MapData>
    <X1>81.82</X1>
    <Y1>40</Y1>
    <X2>81.82</X2>
    <Y2>175</Y2>
    <BorderWidth>2</BorderWidth>
    <BorderColor>Black</BorderColor>
    <BorderStyle />
    <X>5</X>
    <Y>5</Y>
  </Sys_FrmLine>
  <Sys_FrmLine>
    <MyPK>Line1111140255045</MyPK>
    <FK_MapData>ND9004</FK_MapData>
    <X1>81.82</X1>
    <Y1>173.82</Y1>
    <X2>874</X2>
    <Y2>173.82</Y2>
    <BorderWidth>2</BorderWidth>
    <BorderColor>Black</BorderColor>
    <BorderStyle />
    <X>5</X>
    <Y>5</Y>
  </Sys_FrmLine>
  <Sys_FrmLine>
    <MyPK>Line1111140255046</MyPK>
    <FK_MapData>ND9004</FK_MapData>
    <X1>83.36</X1>
    <Y1>40.91</Y1>
    <X2>874</X2>
    <Y2>40.91</Y2>
    <BorderWidth>2</BorderWidth>
    <BorderColor>Black</BorderColor>
    <BorderStyle />
    <X>5</X>
    <Y>5</Y>
  </Sys_FrmLine>
  <Sys_FrmLine>
    <MyPK>Line1111140255047</MyPK>
    <FK_MapData>ND9004</FK_MapData>
    <X1>83.36</X1>
    <Y1>120.91</Y1>
    <X2>873</X2>
    <Y2>120.91</Y2>
    <BorderWidth>2</BorderWidth>
    <BorderColor>Black</BorderColor>
    <BorderStyle />
    <X>5</X>
    <Y>5</Y>
  </Sys_FrmLine>
  <Sys_FrmLine>
    <MyPK>Line1111140255048</MyPK>
    <FK_MapData>ND9004</FK_MapData>
    <X1>873.09</X1>
    <Y1>40</Y1>
    <X2>873.09</X2>
    <Y2>174</Y2>
    <BorderWidth>2</BorderWidth>
    <BorderColor>Black</BorderColor>
    <BorderStyle />
    <X>5</X>
    <Y>5</Y>
  </Sys_FrmLine>
  <Sys_FrmLine>
    <MyPK>Line1111140259170</MyPK>
    <FK_MapData>ND9004</FK_MapData>
    <X1>281.82</X1>
    <Y1>81.82</Y1>
    <X2>281.82</X2>
    <Y2>121.82</Y2>
    <BorderWidth>2</BorderWidth>
    <BorderColor>Black</BorderColor>
    <BorderStyle />
    <X>5</X>
    <Y>5</Y>
  </Sys_FrmLine>
  <Sys_FrmLine>
    <MyPK>Line1111140259171</MyPK>
    <FK_MapData>ND9004</FK_MapData>
    <X1>360</X1>
    <Y1>80.91</Y1>
    <X2>360</X2>
    <Y2>120.91</Y2>
    <BorderWidth>2</BorderWidth>
    <BorderColor>Black</BorderColor>
    <BorderStyle />
    <X>5</X>
    <Y>5</Y>
  </Sys_FrmLine>
  <Sys_FrmLine>
    <MyPK>Line1111140259172</MyPK>
    <FK_MapData>ND9004</FK_MapData>
    <X1>158.82</X1>
    <Y1>41.82</Y1>
    <X2>158.82</X2>
    <Y2>122</Y2>
    <BorderWidth>2</BorderWidth>
    <BorderColor>Black</BorderColor>
    <BorderStyle />
    <X>5</X>
    <Y>5</Y>
  </Sys_FrmLine>
  <Sys_FrmLine>
    <MyPK>Line1111140259173</MyPK>
    <FK_MapData>ND9004</FK_MapData>
    <X1>81.55</X1>
    <Y1>80</Y1>
    <X2>874</X2>
    <Y2>80</Y2>
    <BorderWidth>2</BorderWidth>
    <BorderColor>Black</BorderColor>
    <BorderStyle />
    <X>5</X>
    <Y>5</Y>
  </Sys_FrmLine>
  <Sys_FrmLine>
    <MyPK>Line1111140259174</MyPK>
    <FK_MapData>ND9004</FK_MapData>
    <X1>81.82</X1>
    <Y1>40</Y1>
    <X2>81.82</X2>
    <Y2>213</Y2>
    <BorderWidth>2</BorderWidth>
    <BorderColor>Black</BorderColor>
    <BorderStyle />
    <X>5</X>
    <Y>5</Y>
  </Sys_FrmLine>
  <Sys_FrmLine>
    <MyPK>Line1111140259175</MyPK>
    <FK_MapData>ND9004</FK_MapData>
    <X1>81.82</X1>
    <Y1>173.82</Y1>
    <X2>874</X2>
    <Y2>173.82</Y2>
    <BorderWidth>2</BorderWidth>
    <BorderColor>Black</BorderColor>
    <BorderStyle />
    <X>5</X>
    <Y>5</Y>
  </Sys_FrmLine>
  <Sys_FrmLine>
    <MyPK>Line1111140259176</MyPK>
    <FK_MapData>ND9004</FK_MapData>
    <X1>83.36</X1>
    <Y1>40.91</Y1>
    <X2>874</X2>
    <Y2>40.91</Y2>
    <BorderWidth>2</BorderWidth>
    <BorderColor>Black</BorderColor>
    <BorderStyle />
    <X>5</X>
    <Y>5</Y>
  </Sys_FrmLine>
  <Sys_FrmLine>
    <MyPK>Line1111140259177</MyPK>
    <FK_MapData>ND9004</FK_MapData>
    <X1>83.36</X1>
    <Y1>120.91</Y1>
    <X2>873</X2>
    <Y2>120.91</Y2>
    <BorderWidth>2</BorderWidth>
    <BorderColor>Black</BorderColor>
    <BorderStyle />
    <X>5</X>
    <Y>5</Y>
  </Sys_FrmLine>
  <Sys_FrmLine>
    <MyPK>Line1111140259178</MyPK>
    <FK_MapData>ND9004</FK_MapData>
    <X1>873.09</X1>
    <Y1>40</Y1>
    <X2>873.09</X2>
    <Y2>174</Y2>
    <BorderWidth>2</BorderWidth>
    <BorderColor>Black</BorderColor>
    <BorderStyle />
    <X>5</X>
    <Y>5</Y>
  </Sys_FrmLine>
  <Sys_FrmLab>
    <MyPK>Lab111108032825</MyPK>
    <FK_MapData>ND9004</FK_MapData>
    <Text>申请数量</Text>
    <X>97</X>
    <Y>189</Y>
    <FontSize>14</FontSize>
    <FontColor>#FF000000</FontColor>
    <FontName>Portable User Interface</FontName>
    <FontStyle>Normal</FontStyle>
    <IsBold>0</IsBold>
    <IsItalic>0</IsItalic>
  </Sys_FrmLab>
  <Sys_FrmLab>
    <MyPK>Lab111108032955</MyPK>
    <FK_MapData>ND9004</FK_MapData>
    <Text>领用人</Text>
    <X>290</X>
    <Y>187</Y>
    <FontSize>14</FontSize>
    <FontColor>#FF000000</FontColor>
    <FontName>Portable User Interface</FontName>
    <FontStyle>Normal</FontStyle>
    <IsBold>0</IsBold>
    <IsItalic>0</IsItalic>
  </Sys_FrmLab>
  <Sys_FrmLab>
    <MyPK>Lab111108033120</MyPK>
    <FK_MapData>ND9004</FK_MapData>
    <Text>使用单位</Text>
    <X>651</X>
    <Y>187</Y>
    <FontSize>14</FontSize>
    <FontColor>#FF000000</FontColor>
    <FontName>Portable User Interface</FontName>
    <FontStyle>Normal</FontStyle>
    <IsBold>0</IsBold>
    <IsItalic>0</IsItalic>
  </Sys_FrmLab>
  <Sys_FrmLab>
    <MyPK>Lab111108033324</MyPK>
    <FK_MapData>ND9004</FK_MapData>
    <Text>领取日期</Text>
    <X>464</X>
    <Y>186</Y>
    <FontSize>14</FontSize>
    <FontColor>#FF000000</FontColor>
    <FontName>Portable User Interface</FontName>
    <FontStyle>Normal</FontStyle>
    <IsBold>0</IsBold>
    <IsItalic>0</IsItalic>
  </Sys_FrmLab>
  <Sys_FrmLab>
    <MyPK>Lab1111140253520</MyPK>
    <FK_MapData>ND9004</FK_MapData>
    <Text>流程标题</Text>
    <X>106.5</X>
    <Y>59.22</Y>
    <FontSize>11</FontSize>
    <FontColor>#FF000000</FontColor>
    <FontName>Portable User Interface</FontName>
    <FontStyle>Normal</FontStyle>
    <IsBold>0</IsBold>
    <IsItalic>0</IsItalic>
  </Sys_FrmLab>
  <Sys_FrmLab>
    <MyPK>Lab1111140253521</MyPK>
    <FK_MapData>ND9004</FK_MapData>
    <Text>发起人</Text>
    <X>106.48</X>
    <Y>96.08</Y>
    <FontSize>11</FontSize>
    <FontColor>#FF000000</FontColor>
    <FontName>Portable User Interface</FontName>
    <FontStyle>Normal</FontStyle>
    <IsBold>0</IsBold>
    <IsItalic>0</IsItalic>
  </Sys_FrmLab>
  <Sys_FrmLab>
    <MyPK>Lab1111140253522</MyPK>
    <FK_MapData>ND9004</FK_MapData>
    <Text>发起时间</Text>
    <X>307.64</X>
    <Y>95.17</Y>
    <FontSize>11</FontSize>
    <FontColor>#FF000000</FontColor>
    <FontName>Portable User Interface</FontName>
    <FontStyle>Normal</FontStyle>
    <IsBold>0</IsBold>
    <IsItalic>0</IsItalic>
  </Sys_FrmLab>
  <Sys_FrmLab>
    <MyPK>Lab1111140253523</MyPK>
    <FK_MapData>ND9004</FK_MapData>
    <Text>签约开通</Text>
    <X>365.67</X>
    <Y>6.27</Y>
    <FontSize>23</FontSize>
    <FontColor>#FF000000</FontColor>
    <FontName>Portable User Interface</FontName>
    <FontStyle>Normal</FontStyle>
    <IsBold>0</IsBold>
    <IsItalic>0</IsItalic>
  </Sys_FrmLab>
  <Sys_FrmLab>
    <MyPK>Lab1111140255040</MyPK>
    <FK_MapData>ND9004</FK_MapData>
    <Text>流程标题</Text>
    <X>106.5</X>
    <Y>59.22</Y>
    <FontSize>11</FontSize>
    <FontColor>#FF000000</FontColor>
    <FontName>Portable User Interface</FontName>
    <FontStyle>Normal</FontStyle>
    <IsBold>0</IsBold>
    <IsItalic>0</IsItalic>
  </Sys_FrmLab>
  <Sys_FrmLab>
    <MyPK>Lab1111140255041</MyPK>
    <FK_MapData>ND9004</FK_MapData>
    <Text>发起人</Text>
    <X>106.48</X>
    <Y>96.08</Y>
    <FontSize>11</FontSize>
    <FontColor>#FF000000</FontColor>
    <FontName>Portable User Interface</FontName>
    <FontStyle>Normal</FontStyle>
    <IsBold>0</IsBold>
    <IsItalic>0</IsItalic>
  </Sys_FrmLab>
  <Sys_FrmLab>
    <MyPK>Lab1111140255042</MyPK>
    <FK_MapData>ND9004</FK_MapData>
    <Text>发起时间</Text>
    <X>307.64</X>
    <Y>95.17</Y>
    <FontSize>11</FontSize>
    <FontColor>#FF000000</FontColor>
    <FontName>Portable User Interface</FontName>
    <FontStyle>Normal</FontStyle>
    <IsBold>0</IsBold>
    <IsItalic>0</IsItalic>
  </Sys_FrmLab>
  <Sys_FrmLab>
    <MyPK>Lab1111140255043</MyPK>
    <FK_MapData>ND9004</FK_MapData>
    <Text>签约开通</Text>
    <X>365.67</X>
    <Y>6.27</Y>
    <FontSize>23</FontSize>
    <FontColor>#FF000000</FontColor>
    <FontName>Portable User Interface</FontName>
    <FontStyle>Normal</FontStyle>
    <IsBold>0</IsBold>
    <IsItalic>0</IsItalic>
  </Sys_FrmLab>
  <Sys_FrmLab>
    <MyPK>Lab1111140259170</MyPK>
    <FK_MapData>ND9004</FK_MapData>
    <Text>流程标题</Text>
    <X>106.5</X>
    <Y>59.22</Y>
    <FontSize>11</FontSize>
    <FontColor>#FF000000</FontColor>
    <FontName>Portable User Interface</FontName>
    <FontStyle>Normal</FontStyle>
    <FontWeight>normal</FontWeight>
    <IsBold>0</IsBold>
    <IsItalic>0</IsItalic>
  </Sys_FrmLab>
  <Sys_FrmLab>
    <MyPK>Lab1111140259171</MyPK>
    <FK_MapData>ND9004</FK_MapData>
    <Text>发起人</Text>
    <X>106.48</X>
    <Y>96.08</Y>
    <FontSize>11</FontSize>
    <FontColor>#FF000000</FontColor>
    <FontName>Portable User Interface</FontName>
    <FontStyle>Normal</FontStyle>
    <FontWeight>normal</FontWeight>
    <IsBold>0</IsBold>
    <IsItalic>0</IsItalic>
  </Sys_FrmLab>
  <Sys_FrmLab>
    <MyPK>Lab1111140259172</MyPK>
    <FK_MapData>ND9004</FK_MapData>
    <Text>发起时间</Text>
    <X>307.64</X>
    <Y>95.17</Y>
    <FontSize>11</FontSize>
    <FontColor>#FF000000</FontColor>
    <FontName>Portable User Interface</FontName>
    <FontStyle>Normal</FontStyle>
    <FontWeight>normal</FontWeight>
    <IsBold>0</IsBold>
    <IsItalic>0</IsItalic>
  </Sys_FrmLab>
  <Sys_FrmLab>
    <MyPK>Lab1111140259173</MyPK>
    <FK_MapData>ND9004</FK_MapData>
    <Text>签约开通</Text>
    <X>365.67</X>
    <Y>6.27</Y>
    <FontSize>23</FontSize>
    <FontColor>#FF000000</FontColor>
    <FontName>Portable User Interface</FontName>
    <FontStyle>Normal</FontStyle>
    <FontWeight>normal</FontWeight>
    <IsBold>0</IsBold>
    <IsItalic>0</IsItalic>
  </Sys_FrmLab>
  <Sys_MapAttr>
    <MyPK>ND9004_CDT</MyPK>
    <FK_MapData>ND9004</FK_MapData>
    <KeyOfEn>CDT</KeyOfEn>
    <Name>完成时间</Name>
    <DefVal>@RDT</DefVal>
    <UIContralType>0</UIContralType>
    <MyDataType>7</MyDataType>
    <LGType>0</LGType>
    <UIWidth>100</UIWidth>
    <MinLen>0</MinLen>
    <MaxLen>500</MaxLen>
    <UIBindKey />
    <UIRefKey />
    <UIRefKeyText />
    <UIVisible>0</UIVisible>
    <UIIsEnable>0</UIIsEnable>
    <Tag>1</Tag>
    <IDX>999</IDX>
    <AutoFullDoc />
    <AutoFullWay>0</AutoFullWay>
    <UIIsShowLine>0</UIIsShowLine>
    <UIIsLine>0</UIIsLine>
    <EditType>1</EditType>
    <GroupID>0</GroupID>
    <IsSigan>0</IsSigan>
    <UIHeight>23</UIHeight>
    <X>5</X>
    <Y>5</Y>
  </Sys_MapAttr>
  <Sys_MapAttr>
    <MyPK>ND9004_Emps</MyPK>
    <FK_MapData>ND9004</FK_MapData>
    <KeyOfEn>Emps</KeyOfEn>
    <Name>Emps</Name>
    <DefVal />
    <UIContralType>0</UIContralType>
    <MyDataType>1</MyDataType>
    <LGType>0</LGType>
    <UIWidth>100</UIWidth>
    <MinLen>0</MinLen>
    <MaxLen>400</MaxLen>
    <UIBindKey />
    <UIRefKey />
    <UIRefKeyText />
    <UIVisible>0</UIVisible>
    <UIIsEnable>0</UIIsEnable>
    <Tag />
    <IDX>999</IDX>
    <AutoFullDoc />
    <AutoFullWay>0</AutoFullWay>
    <UIIsShowLine>0</UIIsShowLine>
    <UIIsLine>0</UIIsLine>
    <EditType>1</EditType>
    <GroupID>0</GroupID>
    <IsSigan>0</IsSigan>
    <UIHeight>23</UIHeight>
    <X>5</X>
    <Y>5</Y>
  </Sys_MapAttr>
  <Sys_MapAttr>
    <MyPK>ND9004_fapiao</MyPK>
    <FK_MapData>ND9004</FK_MapData>
    <KeyOfEn>fapiao</KeyOfEn>
    <Name>发票</Name>
    <DefVal />
    <UIContralType>2</UIContralType>
    <MyDataType>4</MyDataType>
    <LGType>0</LGType>
    <UIWidth>100</UIWidth>
    <MinLen>0</MinLen>
    <MaxLen>500</MaxLen>
    <UIBindKey />
    <UIRefKey />
    <UIRefKeyText />
    <UIVisible>1</UIVisible>
    <UIIsEnable>0</UIIsEnable>
    <Tag />
    <IDX>5479</IDX>
    <AutoFullDoc />
    <AutoFullWay>0</AutoFullWay>
    <UIIsShowLine>0</UIIsShowLine>
    <UIIsLine>0</UIIsLine>
    <EditType>0</EditType>
    <GroupID>0</GroupID>
    <IsSigan>0</IsSigan>
    <UIHeight>23</UIHeight>
    <X>204</X>
    <Y>145</Y>
  </Sys_MapAttr>
  <Sys_MapAttr>
    <MyPK>ND9004_faqiren</MyPK>
    <FK_MapData>ND9004</FK_MapData>
    <KeyOfEn>faqiren</KeyOfEn>
    <Name>发起人</Name>
    <DefVal />
    <UIContralType>0</UIContralType>
    <MyDataType>1</MyDataType>
    <LGType>0</LGType>
    <UIWidth>100</UIWidth>
    <MinLen>0</MinLen>
    <MaxLen>200</MaxLen>
    <UIBindKey />
    <UIRefKey />
    <UIRefKeyText />
    <UIVisible>1</UIVisible>
    <UIIsEnable>0</UIIsEnable>
    <Tag />
    <IDX>5480</IDX>
    <AutoFullDoc />
    <AutoFullWay>0</AutoFullWay>
    <UIIsShowLine>0</UIIsShowLine>
    <UIIsLine>0</UIIsLine>
    <EditType>0</EditType>
    <GroupID>0</GroupID>
    <IsSigan>0</IsSigan>
    <UIHeight>23</UIHeight>
    <X>175.56</X>
    <Y>92.43</Y>
  </Sys_MapAttr>
  <Sys_MapAttr>
    <MyPK>ND9004_faqishijian</MyPK>
    <FK_MapData>ND9004</FK_MapData>
    <KeyOfEn>faqishijian</KeyOfEn>
    <Name>发起时间</Name>
    <DefVal />
    <UIContralType>0</UIContralType>
    <MyDataType>7</MyDataType>
    <LGType>0</LGType>
    <UIWidth>100</UIWidth>
    <MinLen>0</MinLen>
    <MaxLen>500</MaxLen>
    <UIBindKey />
    <UIRefKey />
    <UIRefKeyText />
    <UIVisible>1</UIVisible>
    <UIIsEnable>0</UIIsEnable>
    <Tag>1</Tag>
    <IDX>5481</IDX>
    <AutoFullDoc />
    <AutoFullWay>0</AutoFullWay>
    <UIIsShowLine>0</UIIsShowLine>
    <UIIsLine>0</UIIsLine>
    <EditType>0</EditType>
    <GroupID>0</GroupID>
    <IsSigan>0</IsSigan>
    <UIHeight>23</UIHeight>
    <X>384</X>
    <Y>92.43</Y>
  </Sys_MapAttr>
  <Sys_MapAttr>
    <MyPK>ND9004_FID</MyPK>
    <FK_MapData>ND9004</FK_MapData>
    <KeyOfEn>FID</KeyOfEn>
    <Name>FID</Name>
    <DefVal>0</DefVal>
    <UIContralType>0</UIContralType>
    <MyDataType>2</MyDataType>
    <LGType>0</LGType>
    <UIWidth>100</UIWidth>
    <MinLen>0</MinLen>
    <MaxLen>500</MaxLen>
    <UIBindKey />
    <UIRefKey />
    <UIRefKeyText />
    <UIVisible>0</UIVisible>
    <UIIsEnable>0</UIIsEnable>
    <Tag />
    <IDX>999</IDX>
    <AutoFullDoc />
    <AutoFullWay>0</AutoFullWay>
    <UIIsShowLine>0</UIIsShowLine>
    <UIIsLine>0</UIIsLine>
    <EditType>1</EditType>
    <GroupID>0</GroupID>
    <IsSigan>0</IsSigan>
    <UIHeight>23</UIHeight>
    <X>5</X>
    <Y>5</Y>
  </Sys_MapAttr>
  <Sys_MapAttr>
    <MyPK>ND9004_FK_Dept</MyPK>
    <FK_MapData>ND9004</FK_MapData>
    <KeyOfEn>FK_Dept</KeyOfEn>
    <Name>操作员部门</Name>
    <DefVal />
    <UIContralType>1</UIContralType>
    <MyDataType>1</MyDataType>
    <LGType>2</LGType>
    <UIWidth>100</UIWidth>
    <MinLen>0</MinLen>
    <MaxLen>20</MaxLen>
    <UIBindKey>BP.Port.Depts</UIBindKey>
    <UIRefKey />
    <UIRefKeyText />
    <UIVisible>0</UIVisible>
    <UIIsEnable>0</UIIsEnable>
    <Tag />
    <IDX>999</IDX>
    <AutoFullDoc />
    <AutoFullWay>0</AutoFullWay>
    <UIIsShowLine>0</UIIsShowLine>
    <UIIsLine>0</UIIsLine>
    <EditType>1</EditType>
    <GroupID>0</GroupID>
    <IsSigan>0</IsSigan>
    <UIHeight>23</UIHeight>
    <X>5</X>
    <Y>5</Y>
  </Sys_MapAttr>
  <Sys_MapAttr>
    <MyPK>ND9004_hetong</MyPK>
    <FK_MapData>ND9004</FK_MapData>
    <KeyOfEn>hetong</KeyOfEn>
    <Name>合同</Name>
    <DefVal />
    <UIContralType>2</UIContralType>
    <MyDataType>4</MyDataType>
    <LGType>0</LGType>
    <UIWidth>100</UIWidth>
    <MinLen>0</MinLen>
    <MaxLen>500</MaxLen>
    <UIBindKey />
    <UIRefKey />
    <UIRefKeyText />
    <UIVisible>1</UIVisible>
    <UIIsEnable>0</UIIsEnable>
    <Tag />
    <IDX>5482</IDX>
    <AutoFullDoc />
    <AutoFullWay>0</AutoFullWay>
    <UIIsShowLine>0</UIIsShowLine>
    <UIIsLine>0</UIIsLine>
    <EditType>0</EditType>
    <GroupID>0</GroupID>
    <IsSigan>0</IsSigan>
    <UIHeight>23</UIHeight>
    <X>110</X>
    <Y>145</Y>
  </Sys_MapAttr>
  <Sys_MapAttr>
    <MyPK>ND9004_jiamiqi</MyPK>
    <FK_MapData>ND9004</FK_MapData>
    <KeyOfEn>jiamiqi</KeyOfEn>
    <Name>加密器</Name>
    <DefVal />
    <UIContralType>2</UIContralType>
    <MyDataType>4</MyDataType>
    <LGType>0</LGType>
    <UIWidth>100</UIWidth>
    <MinLen>0</MinLen>
    <MaxLen>500</MaxLen>
    <UIBindKey />
    <UIRefKey />
    <UIRefKeyText />
    <UIVisible>1</UIVisible>
    <UIIsEnable>0</UIIsEnable>
    <Tag />
    <IDX>5483</IDX>
    <AutoFullDoc />
    <AutoFullWay>0</AutoFullWay>
    <UIIsShowLine>0</UIIsShowLine>
    <UIIsLine>0</UIIsLine>
    <EditType>0</EditType>
    <GroupID>0</GroupID>
    <IsSigan>0</IsSigan>
    <UIHeight>23</UIHeight>
    <X>292</X>
    <Y>144</Y>
  </Sys_MapAttr>
  <Sys_MapAttr>
    <MyPK>ND9004_jiamiqibianhao</MyPK>
    <FK_MapData>ND9004</FK_MapData>
    <KeyOfEn>jiamiqibianhao</KeyOfEn>
    <Name />
    <UIContralType>0</UIContralType>
    <MyDataType>1</MyDataType>
    <LGType>0</LGType>
    <UIWidth>100</UIWidth>
    <UIBindKey />
    <UIRefKey />
    <UIRefKeyText />
    <UIVisible>1</UIVisible>
    <IDX>1547</IDX>
    <AutoFullDoc />
    <AutoFullWay>0</AutoFullWay>
    <UIIsShowLine>0</UIIsShowLine>
    <UIIsLine>0</UIIsLine>
    <EditType>0</EditType>
    <GroupID>0</GroupID>
    <IsSigan>0</IsSigan>
    <UIHeight>23</UIHeight>
    <X>166</X>
    <Y>187</Y>
  </Sys_MapAttr>
  <Sys_MapAttr>
    <MyPK>ND9004_lingquriqi</MyPK>
    <FK_MapData>ND9004</FK_MapData>
    <KeyOfEn>lingquriqi</KeyOfEn>
    <Name />
    <UIContralType>0</UIContralType>
    <MyDataType>6</MyDataType>
    <LGType>0</LGType>
    <UIWidth>100</UIWidth>
    <UIBindKey />
    <UIRefKey />
    <UIRefKeyText />
    <UIVisible>1</UIVisible>
    <IDX>1548</IDX>
    <AutoFullDoc />
    <AutoFullWay>0</AutoFullWay>
    <UIIsShowLine>0</UIIsShowLine>
    <UIIsLine>0</UIIsLine>
    <EditType>0</EditType>
    <GroupID>0</GroupID>
    <IsSigan>0</IsSigan>
    <UIHeight>23</UIHeight>
    <X>529</X>
    <Y>186</Y>
  </Sys_MapAttr>
  <Sys_MapAttr>
    <MyPK>ND9004_lingyongren</MyPK>
    <FK_MapData>ND9004</FK_MapData>
    <KeyOfEn>lingyongren</KeyOfEn>
    <Name />
    <DefVal />
    <UIContralType>0</UIContralType>
    <MyDataType>1</MyDataType>
    <LGType>0</LGType>
    <UIWidth>100</UIWidth>
    <MinLen>0</MinLen>
    <MaxLen>500</MaxLen>
    <UIBindKey />
    <UIRefKey />
    <UIRefKeyText />
    <UIVisible>1</UIVisible>
    <UIIsEnable>1</UIIsEnable>
    <Tag />
    <IDX>1549</IDX>
    <AutoFullDoc />
    <AutoFullWay>0</AutoFullWay>
    <UIIsShowLine>0</UIIsShowLine>
    <UIIsLine>0</UIIsLine>
    <EditType>0</EditType>
    <GroupID>0</GroupID>
    <IsSigan>0</IsSigan>
    <UIHeight>23</UIHeight>
    <X>342</X>
    <Y>185</Y>
  </Sys_MapAttr>
  <Sys_MapAttr>
    <MyPK>ND9004_OID</MyPK>
    <FK_MapData>ND9004</FK_MapData>
    <KeyOfEn>OID</KeyOfEn>
    <Name>WorkID</Name>
    <DefVal>0</DefVal>
    <UIContralType>0</UIContralType>
    <MyDataType>2</MyDataType>
    <LGType>0</LGType>
    <UIWidth>100</UIWidth>
    <MinLen>0</MinLen>
    <MaxLen>500</MaxLen>
    <UIBindKey />
    <UIRefKey />
    <UIRefKeyText />
    <UIVisible>0</UIVisible>
    <UIIsEnable>0</UIIsEnable>
    <Tag />
    <IDX>999</IDX>
    <AutoFullDoc />
    <AutoFullWay>0</AutoFullWay>
    <UIIsShowLine>0</UIIsShowLine>
    <UIIsLine>0</UIIsLine>
    <EditType>2</EditType>
    <GroupID>0</GroupID>
    <IsSigan>0</IsSigan>
    <UIHeight>23</UIHeight>
    <X>5</X>
    <Y>5</Y>
  </Sys_MapAttr>
  <Sys_MapAttr>
    <MyPK>ND9004_RDT</MyPK>
    <FK_MapData>ND9004</FK_MapData>
    <KeyOfEn>RDT</KeyOfEn>
    <Name>接受时间</Name>
    <DefVal />
    <UIContralType>0</UIContralType>
    <MyDataType>7</MyDataType>
    <LGType>0</LGType>
    <UIWidth>100</UIWidth>
    <MinLen>0</MinLen>
    <MaxLen>500</MaxLen>
    <UIBindKey />
    <UIRefKey />
    <UIRefKeyText />
    <UIVisible>0</UIVisible>
    <UIIsEnable>0</UIIsEnable>
    <Tag>1</Tag>
    <IDX>999</IDX>
    <AutoFullDoc />
    <AutoFullWay>0</AutoFullWay>
    <UIIsShowLine>0</UIIsShowLine>
    <UIIsLine>0</UIIsLine>
    <EditType>1</EditType>
    <GroupID>0</GroupID>
    <IsSigan>0</IsSigan>
    <UIHeight>23</UIHeight>
    <X>5</X>
    <Y>5</Y>
  </Sys_MapAttr>
  <Sys_MapAttr>
    <MyPK>ND9004_Rec</MyPK>
    <FK_MapData>ND9004</FK_MapData>
    <KeyOfEn>Rec</KeyOfEn>
    <Name>记录人</Name>
    <DefVal>@WebUser.No</DefVal>
    <UIContralType>0</UIContralType>
    <MyDataType>1</MyDataType>
    <LGType>0</LGType>
    <UIWidth>100</UIWidth>
    <MinLen>0</MinLen>
    <MaxLen>20</MaxLen>
    <UIBindKey />
    <UIRefKey />
    <UIRefKeyText />
    <UIVisible>0</UIVisible>
    <UIIsEnable>0</UIIsEnable>
    <Tag />
    <IDX>999</IDX>
    <AutoFullDoc />
    <AutoFullWay>0</AutoFullWay>
    <UIIsShowLine>0</UIIsShowLine>
    <UIIsLine>0</UIIsLine>
    <EditType>1</EditType>
    <GroupID>0</GroupID>
    <IsSigan>0</IsSigan>
    <UIHeight>23</UIHeight>
    <X>5</X>
    <Y>5</Y>
  </Sys_MapAttr>
  <Sys_MapAttr>
    <MyPK>ND9004_shiyongdanwei</MyPK>
    <FK_MapData>ND9004</FK_MapData>
    <KeyOfEn>shiyongdanwei</KeyOfEn>
    <Name />
    <UIContralType>0</UIContralType>
    <MyDataType>1</MyDataType>
    <LGType>0</LGType>
    <UIWidth>100</UIWidth>
    <UIBindKey />
    <UIRefKey />
    <UIRefKeyText />
    <UIVisible>1</UIVisible>
    <IDX>1550</IDX>
    <AutoFullDoc />
    <AutoFullWay>0</AutoFullWay>
    <UIIsShowLine>0</UIIsShowLine>
    <UIIsLine>0</UIIsLine>
    <EditType>0</EditType>
    <GroupID>0</GroupID>
    <IsSigan>0</IsSigan>
    <UIHeight>23</UIHeight>
    <X>717</X>
    <Y>186</Y>
  </Sys_MapAttr>
  <Sys_MapAttr>
    <MyPK>ND9004_Title</MyPK>
    <FK_MapData>ND9004</FK_MapData>
    <KeyOfEn>Title</KeyOfEn>
    <Name>标题</Name>
    <DefVal />
    <UIContralType>0</UIContralType>
    <MyDataType>1</MyDataType>
    <LGType>0</LGType>
    <UIWidth>251</UIWidth>
    <MinLen>0</MinLen>
    <MaxLen>200</MaxLen>
    <UIBindKey />
    <UIRefKey />
    <UIRefKeyText />
    <UIVisible>1</UIVisible>
    <UIIsEnable>0</UIIsEnable>
    <Tag />
    <IDX>5430</IDX>
    <AutoFullDoc />
    <AutoFullWay>0</AutoFullWay>
    <UIIsShowLine>0</UIIsShowLine>
    <UIIsLine>1</UIIsLine>
    <EditType>0</EditType>
    <GroupID>0</GroupID>
    <IsSigan>0</IsSigan>
    <UIHeight>23</UIHeight>
    <X>173.83</X>
    <Y>55.4</Y>
  </Sys_MapAttr>
  <Sys_GroupField>
    <OID>104985</OID>
    <Lab>加密器领用申请</Lab>
    <EnName>ND9004</EnName>
    <Idx>0</Idx>
  </Sys_GroupField>
</NewDataSet>